timeseries/__init__.py
timeseries/time_series_estimator.py
tseries/__init__.py
tseries/time_series_estimator.py
tseries-0.1.1.dist-info/DESCRIPTION.rst
tseries-0.1.1.dist-info/METADATA
tseries-0.1.1.dist-info/RECORD
tseries-0.1.1.dist-info/WHEEL
tseries-0.1.1.dist-info/metadata.json
tseries-0.1.1.dist-info/top_level.txt
