Metadata-Version: 2.0
Name: tseries
Version: 0.1.1
Summary: A package for analyzing time series with scikit-learn
Home-page: https://github.com/mhamilton723/TimeSeriesRegressor
Author: Mark Hamilton
Author-email: mhamilton723@gmail.com
License: UNKNOWN
Platform: UNKNOWN
